clappform_integrations/__init__.py
clappform_integrations/clappform_itris/src/clappform_itris/__init__.py
clappform_integrations/clappform_itsperfect/src/clappform_itsperfect/__init__.py
clappform_integrations/clappform_rudholm/src/clappform_rudholm/__init__.py
clappform_integrations/clappform_transus/src/clappform_transus/__init__.py
clappform_integrations-1.0.31.dist-info/LICENSE
clappform_integrations-1.0.31.dist-info/METADATA
clappform_integrations-1.0.31.dist-info/WHEEL
clappform_integrations-1.0.31.dist-info/top_level.txt
clappform_integrations-1.0.31.dist-info/RECORD
