Metadata-Version: 2.1
Name: clappform-integrations
Version: 1.0.31
Summary: Clappform Python API wrapper
Author-email: "Clappform B.V." <info@clappform.com>
Project-URL: Documentation, https://clappform.readthedocs.io
Project-URL: Source, https://github.com/ClappFormOrg/clappform-integrations
Classifier: Development Status :: 4 - Beta
Classifier: License :: OSI Approved :: MIT License
Classifier: Programming Language :: Python :: 3
Classifier: Operating System :: OS Independent
Requires-Python: >=3.10
License-File: LICENSE
Requires-Dist: requests ==2.31.0
Requires-Dist: pandas ==1.5.2
Requires-Dist: xmltodict ==0.13.0
Requires-Dist: beautifulsoup4 ==4.12.2
